{
    "attributeList": [],
    "containedResourcesList": [],
    "filterInstancesList": [],
    "message": [],
    "metricList": [],
    "postprocessor": [],
    "report": [
        {
            "metric": {
                "description": "unreferenced interval count by MVS image",
                "filter": "HI=20;ORD=VD",
                "format": "list",
                "id": "8D1FE0",
                "listtype": "M",
                "numcols": 2,
                "unit": "seconds",
                "workscope": ",,G"
            },
            "resource": {
                "reslabel": ",SYPLEX01,SYSPLEX",
                "reslabelurl": ",SYPLEX01,SYSPLEX",
                "restype": "SYSPLEX"
            },
            "row": [
                {
                    "attributes": "YES",
                    "col": [
                        "SY21",
                        "65535"
                    ],
                    "percent": "100",
                    "refno": 1
                },
                {
                    "attributes": "YES",
                    "col": [
                        "SY22",
                        "65535"
                    ],
                    "percent": "100",
                    "refno": 2
                },
                {
                    "attributes": "YES",
                    "col": [
                        "SY23",
                        "65535"
                    ],
                    "percent": "100",
                    "refno": 3
                },
                {
                    "attributes": "YES",
                    "col": [
                        "SY25",
                        "65535"
                    ],
                    "percent": "100",
                    "refno": 4
                },
                {
                    "attributes": "YES",
                    "col": [
                        "SY26",
                        "65535"
                    ],
                    "percent": "100",
                    "refno": 5
                },
                {
                    "attributes": "YES",
                    "col": [
                        "SY27",
                        "65535"
                    ],
                    "percent": "100",
                    "refno": 6
                },
                {
                    "attributes": "YES",
                    "col": [
                        "SY28",
                        "65535"
                    ],
                    "percent": "100",
                    "refno": 7
                }
            ],
            "timeData": {
                "dataRange": {
                    "unit": "SECONDS",
                    "value": 60
                },
                "displayEnd": {
                    "locale": "en-us",
                    "value": "07/10/2026 05:13:00"
                },
                "displayStart": {
                    "locale": "en-us",
                    "value": "07/10/2026 05:12:00"
                },
                "gathererInterval": {
                    "unit": "SECONDS",
                    "value": 60
                },
                "localEnd": "20260710051300",
                "localNext": "20260710051330",
                "localPrev": "20260710051130",
                "localStart": "20260710051200",
                "utcEnd": "20260710091300",
                "utcStart": "20260710091200"
            }
        }
    ],
    "server": {
        "functionality": "3650",
        "name": "RMF-DDS-Server",
        "platform": "z/OS",
        "version": "03.02.00"
    },
    "workscopeList": []
}
